algmonbody/__init__.py
algmonbody/core.py
algmonbody/setup.py
algmonbrain/__init__.py
algmonbrain/core.py
algmonbrain/setup.py
algmonpositiveflow-0.0.1.dist-info/METADATA
algmonpositiveflow-0.0.1.dist-info/WHEEL
algmonpositiveflow-0.0.1.dist-info/top_level.txt
algmonpositiveflow-0.0.1.dist-info/RECORD
