Metadata-Version: 2.1
Name: algmonpositiveflow
Version: 0.0.1
Summary: the algmon positive flow toolkit
Home-page: 
Author: algmon
Author-email: support@algmon.com
Classifier: Topic :: Scientific/Engineering :: Artificial Intelligence
Classifier: Development Status :: 1 - Planning
Classifier: Environment :: Console
Classifier: Intended Audience :: Developers
Classifier: License :: OSI Approved :: Apache Software License
Classifier: Natural Language :: English
Classifier: Operating System :: OS Independent
Classifier: Programming Language :: Python :: 3
